ultrasmtp/__init__.py
ultrasmtp/sendemail.py
ultrasmtp-1.0.0.dist-info/LICENSE.rst
ultrasmtp-1.0.0.dist-info/METADATA
ultrasmtp-1.0.0.dist-info/WHEEL
ultrasmtp-1.0.0.dist-info/top_level.txt
ultrasmtp-1.0.0.dist-info/RECORD
