Metadata-Version: 2.1
Name: ultrasmtp
Version: 1.0.0
Summary: UltraSMTP is a lightweight Python library for sending emails with attachments and HTML templates. It provides easy configuration for common SMTP settings and offers template-based email rendering.
Home-page: https://github.com/Kawai-Senpai/UltraSMTP
Download-URL: https://github.com/Kawai-Senpai/UltraSMTP
Author: Ranit Bhowmick
Author-email: bhowmickranitking@duck.com
License: MIT License with attribution requirement
Keywords: Email,SMTP,HTML Email,Email Templates,Email Attachments,Email Sender
License-File: LICENSE.rst
